devtools_placeholder/__init__.py
devtools_placeholder-1.0.1.dist-info/METADATA
devtools_placeholder-1.0.1.dist-info/WHEEL
devtools_placeholder-1.0.1.dist-info/top_level.txt
devtools_placeholder-1.0.1.dist-info/RECORD
