Metadata-Version: 2.1
Name: devtools_placeholder
Version: 1.0.1
Summary: Placeholder image generator
Home-page: https://devtools.at/tools/placeholder-image
Author: DevTools.at
Author-email: hello@devtools.at
Project-URL: Homepage, https://devtools.at/tools/placeholder-image
Project-URL: Repository, https://github.com/devtools-at/placeholder-image
Classifier: Development Status :: 4 - Beta
Classifier: Intended Audience :: Developers
Classifier: License :: OSI Approved :: MIT License
Classifier: Programming Language :: Python :: 3
Requires-Python: >=3.8
